mplfontutils/__init__.py
mplfontutils/__main__.py
mplfontutils/core.py
mplfontutils-0.1.0.dist-info/METADATA
mplfontutils-0.1.0.dist-info/WHEEL
mplfontutils-0.1.0.dist-info/entry_points.txt
mplfontutils-0.1.0.dist-info/licenses/LICENSE
mplfontutils-0.1.0.dist-info/RECORD
